natural_key_cache/__init__.py
natural_key_cache/cache_manager.py
django_natural_key_cache-0.4.dist-info/top_level.txt
django_natural_key_cache-0.4.dist-info/METADATA
django_natural_key_cache-0.4.dist-info/DESCRIPTION.rst
django_natural_key_cache-0.4.dist-info/metadata.json
django_natural_key_cache-0.4.dist-info/WHEEL
django_natural_key_cache-0.4.dist-info/RECORD
