Metadata-Version: 2.0
Name: django-natural-key-cache
Version: 0.4
Summary: Cache manager for caching django models by natural keys
Home-page: https://github.com/shadowfax-chc/django-natural-key-cache
Author: Timothy Messier
Author-email: tim.messier@gmail.com
License: ISC License
Keywords: django-natural-key-cache
Platform: UNKNOWN
Classifier: Development Status :: 1 - Planning
Classifier: Intended Audience :: Developers
Classifier: Natural Language :: English
Classifier: Programming Language :: Python :: 2
Classifier: Programming Language :: Python :: 2.7
Requires-Dist: Django (>=1.8)
